colorcodes/__init__.py
colorcodes/colorcodes.py
colorcodes_elunico-1.0.0.dist-info/METADATA
colorcodes_elunico-1.0.0.dist-info/WHEEL
colorcodes_elunico-1.0.0.dist-info/top_level.txt
colorcodes_elunico-1.0.0.dist-info/RECORD
