Metadata-Version: 2.1
Name: colorcodes-elunico
Version: 1.0.0
Summary: A flexible utiltity for printing out text in various colors and styles
Home-page: https://github.com/elunico/colorcodes
Author: Thomas Povinelli
Author-email: tompov227@gmail.com
Classifier: Programming Language :: Python :: 3
Classifier: License :: OSI Approved :: MIT License
Classifier: Operating System :: OS Independent
Requires-Python: >=3.11
